<?xml version="1.0" encoding="utf-8" ?>
<dwsync>
<file name="airbnb-payment.png" server="www.jdon.com//home/jdon/html/" local="133118202210000000" remote="133118202210000000" Dst="0" />
<file name="api-mesh.gif" server="www.jdon.com//home/jdon/html/" local="133118202210000000" remote="133118202210000000" Dst="0" />
<file name="api-mesh2.gif" server="www.jdon.com//home/jdon/html/" local="133118202210000000" remote="133118202210000000" Dst="0" />
<file name="api-mesh3.gif" server="www.jdon.com//home/jdon/html/" local="133118202210000000" remote="133118202210000000" Dst="0" />
<file name="bem.png" server="www.jdon.com//home/jdon/html/" local="133118202220000000" remote="133118202220000000" Dst="0" />
<file name="Changed-Default-Ports-for-Hadoop-3-Hadoop-3.png" server="www.jdon.com//home/jdon/html/" local="133118202220000000" remote="133118202220000000" Dst="0" />
<file name="codeReadable.png" server="www.jdon.com//home/jdon/html/" local="133118202220000000" remote="133118202220000000" Dst="0" />
<file name="coderoute.gif" server="www.jdon.com//home/jdon/html/" local="133118202220000000" remote="133118202220000000" Dst="0" />
<file name="complex_complicated.png" server="www.jdon.com//home/jdon/html/" local="133118202220000000" remote="133118202220000000" Dst="0" />
<file name="CryptoPunks.png" server="www.jdon.com//home/jdon/html/" local="133118202220000000" remote="133118202220000000" Dst="0" />
<file name="Cynefin.png" server="www.jdon.com//home/jdon/html/" local="133118202220000000" remote="133118202220000000" Dst="0" />
<file name="data_lake.png" server="www.jdon.com//home/jdon/html/" local="133118202220000000" remote="133118202220000000" Dst="0" />
<file name="ddd-entity-vo.png" server="www.jdon.com//home/jdon/html/" local="133118202220000000" remote="133118202220000000" Dst="0" />
<file name="DDD-MRP.gif" server="www.jdon.com//home/jdon/html/" local="133118202220000000" remote="133118202220000000" Dst="0" />
<file name="ddd_springboot_account.png" server="www.jdon.com//home/jdon/html/" local="133118202220000000" remote="133118202220000000" Dst="0" />
<file name="ddd_springboot_account2.png" server="www.jdon.com//home/jdon/html/" local="133118202220000000" remote="133118202220000000" Dst="0" />
<file name="ddd_springboot_de.png" server="www.jdon.com//home/jdon/html/" local="133118202220000000" remote="133118202220000000" Dst="0" />
<file name="ddd_springboot_de2.png" server="www.jdon.com//home/jdon/html/" local="133118202220000000" remote="133118202220000000" Dst="0" />
<file name="ddd_springboot_de3.png" server="www.jdon.com//home/jdon/html/" local="133118202220000000" remote="133118202220000000" Dst="0" />
<file name="ddd_springboot_delivery.png" server="www.jdon.com//home/jdon/html/" local="133118202220000000" remote="133118202220000000" Dst="0" />
<file name="ddd_springboot_delivery2.png" server="www.jdon.com//home/jdon/html/" local="133118202220000000" remote="133118202220000000" Dst="0" />
<file name="ddd_springboot_kiali.png" server="www.jdon.com//home/jdon/html/" local="133118202220000000" remote="133118202220000000" Dst="0" />
<file name="ddd_springboot_order.png" server="www.jdon.com//home/jdon/html/" local="133118202220000000" remote="133118202220000000" Dst="0" />
<file name="ddd_springboot_order2.png" server="www.jdon.com//home/jdon/html/" local="133118202220000000" remote="133118202220000000" Dst="0" />
<file name="ddd_springboot_orderservice.jpg" server="www.jdon.com//home/jdon/html/" local="133118202220000000" remote="133118202220000000" Dst="0" />
<file name="ddd_springboot_orderservice2.png" server="www.jdon.com//home/jdon/html/" local="133118202220000000" remote="133118202220000000" Dst="0" />
<file name="de_lease.png" server="www.jdon.com//home/jdon/html/" local="133118202220000000" remote="133118202220000000" Dst="0" />
<file name="de_lease2.png" server="www.jdon.com//home/jdon/html/" local="133118202220000000" remote="133118202220000000" Dst="0" />
<file name="de_lease3.png" server="www.jdon.com//home/jdon/html/" local="133118202220000000" remote="133118202220000000" Dst="0" />
<file name="decoupled-transactions3.gif" server="www.jdon.com//home/jdon/html/" local="133118202220000000" remote="133118202220000000" Dst="0" />
<file name="dnn.png" server="www.jdon.com//home/jdon/html/" local="133118202220000000" remote="133118202220000000" Dst="0" />
<file name="domainp.png" server="www.jdon.com//home/jdon/html/" local="133118202220000000" remote="133118202220000000" Dst="0" />
<file name="eventstorming625.png" server="www.jdon.com//home/jdon/html/" local="133118202220000000" remote="133118202220000000" Dst="0" />
<file name="eventstorming6251.png" server="www.jdon.com//home/jdon/html/" local="133118202220000000" remote="133118202220000000" Dst="0" />
<file name="eventstorming6252.png" server="www.jdon.com//home/jdon/html/" local="133118202220000000" remote="133118202220000000" Dst="0" />
<file name="eventstorming6253.png" server="www.jdon.com//home/jdon/html/" local="133118202220000000" remote="133118202220000000" Dst="0" />
<file name="eventstorming6254.png" server="www.jdon.com//home/jdon/html/" local="133118202220000000" remote="133118202220000000" Dst="0" />
<file name="five_architect1.png" server="www.jdon.com//home/jdon/html/" local="133118202220000000" remote="133118202220000000" Dst="0" />
<file name="five_architect2.png" server="www.jdon.com//home/jdon/html/" local="133118202220000000" remote="133118202220000000" Dst="0" />
<file name="five_architect3.png" server="www.jdon.com//home/jdon/html/" local="133118202220000000" remote="133118202220000000" Dst="0" />
<file name="five_architect4.png" server="www.jdon.com//home/jdon/html/" local="133118202220000000" remote="133118202220000000" Dst="0" />
<file name="five_architect5.png" server="www.jdon.com//home/jdon/html/" local="133118202220000000" remote="133118202220000000" Dst="0" />
<file name="followme.jpg" server="www.jdon.com//home/jdon/html/" local="133118202220000000" remote="133118202220000000" Dst="0" />
<file name="i-space.png" server="www.jdon.com//home/jdon/html/" local="133118202220000000" remote="133118202220000000" Dst="0" />
<file name="IMG_0867.png" server="www.jdon.com//home/jdon/html/" local="133118202230000000" remote="133118202230000000" Dst="0" />
<file name="markov.gif" server="www.jdon.com//home/jdon/html/" local="133118202230000000" remote="133118202230000000" Dst="0" />
<file name="markov2.gif" server="www.jdon.com//home/jdon/html/" local="133118202230000000" remote="133118202230000000" Dst="0" />
<file name="markov3.gif" server="www.jdon.com//home/jdon/html/" local="133118202230000000" remote="133118202230000000" Dst="0" />
<file name="markov4.gif" server="www.jdon.com//home/jdon/html/" local="133118202230000000" remote="133118202230000000" Dst="0" />
<file name="markov5.gif" server="www.jdon.com//home/jdon/html/" local="133118202230000000" remote="133118202230000000" Dst="0" />
<file name="mircoservicesmodeling.jpg" server="www.jdon.com//home/jdon/html/" local="133118202230000000" remote="133118202230000000" Dst="0" />
<file name="ml-dataset.png" server="www.jdon.com//home/jdon/html/" local="133118202230000000" remote="133118202230000000" Dst="0" />
<file name="ml.png" server="www.jdon.com//home/jdon/html/" local="133118202230000000" remote="133118202230000000" Dst="0" />
<file name="mongodbperformance.png" server="www.jdon.com//home/jdon/html/" local="133118202230000000" remote="133118202230000000" Dst="0" />
<file name="ocp-rule.gif" server="www.jdon.com//home/jdon/html/" local="133118202230000000" remote="133118202230000000" Dst="0" />
<file name="port_adaptor.png" server="www.jdon.com//home/jdon/html/" local="133118202230000000" remote="133118202230000000" Dst="0" />
<file name="port_adaptor2.png" server="www.jdon.com//home/jdon/html/" local="133118202230000000" remote="133118202230000000" Dst="0" />
<file name="port_adaptor3.png" server="www.jdon.com//home/jdon/html/" local="133118202230000000" remote="133118202230000000" Dst="0" />
<file name="servicemodeling2.gif" server="www.jdon.com//home/jdon/html/" local="133118202230000000" remote="133118202230000000" Dst="0" />
<file name="six-ddd.gif" server="www.jdon.com//home/jdon/html/" local="133118202230000000" remote="133118202230000000" Dst="0" />
<file name="spark-graphx.png" server="www.jdon.com//home/jdon/html/" local="133118202230000000" remote="133118202230000000" Dst="0" />
<file name="spark-stream.png" server="www.jdon.com//home/jdon/html/" local="133118202230000000" remote="133118202230000000" Dst="0" />
<file name="streamjava8.gif" server="www.jdon.com//home/jdon/html/" local="133118202230000000" remote="133118202230000000" Dst="0" />
<file name="traditionalpg.png" server="www.jdon.com//home/jdon/html/" local="133118202230000000" remote="133118202230000000" Dst="0" />
<file name="walmart-notify.png" server="www.jdon.com//home/jdon/html/" local="133118202230000000" remote="133118202230000000" Dst="0" />
<file name="walmart-notify2.png" server="www.jdon.com//home/jdon/html/" local="133118202230000000" remote="133118202230000000" Dst="0" />
<file name="walmart-notify3.png" server="www.jdon.com//home/jdon/html/" local="133118202230000000" remote="133118202230000000" Dst="0" />
<file name="webhooks.png" server="www.jdon.com//home/jdon/html/" local="133118202230000000" remote="133118202230000000" Dst="0" />
</dwsync>